pyfunctional/__init__.py
pyfunctional/pftyping.py
pyfunctional/pyfunctional.py
pyfunctional_elunico-0.16.0.dist-info/LICENSE
pyfunctional_elunico-0.16.0.dist-info/METADATA
pyfunctional_elunico-0.16.0.dist-info/WHEEL
pyfunctional_elunico-0.16.0.dist-info/top_level.txt
pyfunctional_elunico-0.16.0.dist-info/RECORD
