Metadata-Version: 2.1
Name: pyfunctional-elunico
Version: 0.16.0
Summary: A small collection of functions I find useful
Home-page: https://github.com/elunico/pyfunctional
Author: Thomas Povinelli
Author-email: tompov227@gmail.com
Classifier: Programming Language :: Python :: 3
Classifier: License :: OSI Approved :: MIT License
Classifier: Operating System :: OS Independent
Requires-Python: >=3.7
License-File: LICENSE
